CHANGES.txt
MANIFEST.in
README.md
setup.py
wheelcms.egg-info/PKG-INFO
wheelcms.egg-info/SOURCES.txt
wheelcms.egg-info/dependency_links.txt
wheelcms.egg-info/namespace_packages.txt
wheelcms.egg-info/not-zip-safe
wheelcms.egg-info/requires.txt
wheelcms.egg-info/top_level.txt
wheelcms/wheelcms/__init__.py