Metadata-Version: 1.1
Name: wheelcms
Version: 0.8.0
Summary: Overall package for WheelCMS
Home-page: http://github.com/wheelcms/wheelcms
Author: Ivo van der Wijk
Author-email: wheelcms@in.m3r.nl
License: BSD
Platform: UNKNOWN
Classifier: Programming Language :: Python
